odoo/addons/account_invoice_inter_company/README.rst
odoo/addons/account_invoice_inter_company/__init__.py
odoo/addons/account_invoice_inter_company/__manifest__.py
odoo/addons/account_invoice_inter_company/i18n/account_invoice_inter_company.pot
odoo/addons/account_invoice_inter_company/i18n/de.po
odoo/addons/account_invoice_inter_company/i18n/fr.po
odoo/addons/account_invoice_inter_company/i18n/hr.po
odoo/addons/account_invoice_inter_company/i18n/it.po
odoo/addons/account_invoice_inter_company/i18n/sk.po
odoo/addons/account_invoice_inter_company/i18n/sk_SK.po
odoo/addons/account_invoice_inter_company/i18n/zh_CN.po
odoo/addons/account_invoice_inter_company/models/__init__.py
odoo/addons/account_invoice_inter_company/models/account_invoice.py
odoo/addons/account_invoice_inter_company/models/res_company.py
odoo/addons/account_invoice_inter_company/models/res_config_settings.py
odoo/addons/account_invoice_inter_company/readme/CONFIGURE.rst
odoo/addons/account_invoice_inter_company/readme/CONTRIBUTORS.rst
odoo/addons/account_invoice_inter_company/readme/DESCRIPTION.rst
odoo/addons/account_invoice_inter_company/readme/ROADMAP.rst
odoo/addons/account_invoice_inter_company/static/description/icon.png
odoo/addons/account_invoice_inter_company/static/description/index.html
odoo/addons/account_invoice_inter_company/tests/__init__.py
odoo/addons/account_invoice_inter_company/tests/inter_company_invoice.xml
odoo/addons/account_invoice_inter_company/tests/test_inter_company_invoice.py
odoo/addons/account_invoice_inter_company/views/account_invoice_views.xml
odoo/addons/account_invoice_inter_company/views/res_config_settings_view.xml
odoo12_addon_account_invoice_inter_company-12.0.2.1.3.dist-info/METADATA
odoo12_addon_account_invoice_inter_company-12.0.2.1.3.dist-info/WHEEL
odoo12_addon_account_invoice_inter_company-12.0.2.1.3.dist-info/top_level.txt
odoo12_addon_account_invoice_inter_company-12.0.2.1.3.dist-info/RECORD
