Metadata-Version: 2.1
Name: odoo12-addon-account-invoice-inter-company
Version: 12.0.2.1.3
Summary: Intercompany invoice rules
Home-page: https://github.com/OCA/multi-company
Author: Odoo SA, Akretion, Odoo Community Association (OCA)
Author-email: support@odoo-community.org
License: AGPL-3
Platform: UNKNOWN
Classifier: Programming Language :: Python
Classifier: Framework :: Odoo
Classifier: License :: OSI Approved :: GNU Affero General Public License v3
Requires-Python: >=3.5
Requires-Dist: odoo (<12.1dev,>=12.0a)
